README.rst
setup.py
pygain/__init__.py
pygain/gain.py
pygain.egg-info/PKG-INFO
pygain.egg-info/SOURCES.txt
pygain.egg-info/dependency_links.txt
pygain.egg-info/not-zip-safe
pygain.egg-info/requires.txt
pygain.egg-info/top_level.txt