Metadata-Version: 1.1
Name: pygain
Version: 3.1.9
Summary: import module from the sky
Home-page: https://github.com/shawhen/pygain
Author: zig
Author-email: remember1637@gmail.com
License: BSD
Platform: UNKNOWN
Classifier: Topic :: Software Development :: Libraries :: Python Modules
Classifier: Intended Audience :: Developers
Classifier: License :: OSI Approved :: BSD License
Classifier: Operating System :: OS Independent
Classifier: Programming Language :: Python
